pyCoilGen/__init__.py
pyCoilGen/__main__.py
pyCoilGen/pyCoilGen_release.py
pyCoilGen/export_factory/__init__.py
pyCoilGen/export_factory/export_cad_file.py
pyCoilGen/helpers/__init__.py
pyCoilGen/helpers/common.py
pyCoilGen/helpers/convert_matlabdata_to_numpy.py
pyCoilGen/helpers/extraction.py
pyCoilGen/helpers/persistence.py
pyCoilGen/helpers/pyshull.py
pyCoilGen/helpers/timing.py
pyCoilGen/helpers/triangulation.py
pyCoilGen/helpers/visualisation.py
pyCoilGen/mesh_factory/__init__.py
pyCoilGen/mesh_factory/build_biplanar_mesh.py
pyCoilGen/mesh_factory/build_circular_mesh.py
pyCoilGen/mesh_factory/build_cut_circle.py
pyCoilGen/mesh_factory/build_cut_rectangle.py
pyCoilGen/mesh_factory/build_cylinder_mesh.py
pyCoilGen/mesh_factory/build_planar_mesh.py
pyCoilGen/mesh_factory/create_stl_mesh.py
pyCoilGen/plotting/__init__.py
pyCoilGen/plotting/plot_2D_contours_with_sf.py
pyCoilGen/plotting/plot_3D_contours_with_sf.py
pyCoilGen/plotting/plot_contours_with_field.py
pyCoilGen/plotting/plot_error_different_solutions.py
pyCoilGen/plotting/plot_various_error_metrics.py
pyCoilGen/plotting/plot_vector_field.py
pyCoilGen/sub_functions/__init__.py
pyCoilGen/sub_functions/calc_3d_rotation_matrix_by_vector.py
pyCoilGen/sub_functions/calc_contours_by_triangular_potential_cuts.py
pyCoilGen/sub_functions/calc_gradient_along_vector.py
pyCoilGen/sub_functions/calc_local_opening_gab.py
pyCoilGen/sub_functions/calc_mean_loop_normal.py
pyCoilGen/sub_functions/calc_plane_line_intersection.py
pyCoilGen/sub_functions/calc_potential_levels.py
pyCoilGen/sub_functions/calculate_basis_functions.py
pyCoilGen/sub_functions/calculate_boundary_criteria_matrix.py
pyCoilGen/sub_functions/calculate_force_and_torque_matrix.py
pyCoilGen/sub_functions/calculate_gradient.py
pyCoilGen/sub_functions/calculate_gradient_sensitivity_matrix.py
pyCoilGen/sub_functions/calculate_group_centers.py
pyCoilGen/sub_functions/calculate_inductance_by_coil_layout.py
pyCoilGen/sub_functions/calculate_one_ring_by_mesh.py
pycoilgen-0.2.3.dist-info/entry_points.txt
pycoilgen-0.2.3.dist-info/LICENSE.txt
pycoilgen-0.2.3.dist-info/WHEEL
pycoilgen-0.2.3.dist-info/METADATA
pycoilgen-0.2.3.dist-info/RECORD
